island_backup/__init__.py
island_backup/_version.py
island_backup/island_switcher.py
island_backup/main.py
island_backup/network.py
island_backup/settings.py
island_backup/utils.py
island_backup/islands/__init__.py
island_backup/islands/adnmb.py
island_backup/islands/bases.py
island_backup/islands/kukuku.py
island_backup/islands/mixins.py
island_backup/islands/nimingban.py
island_backup/islands/the2chan.py
island_backup/islands/the4chan.py
island_backup/templates/base.html
island_backup/templates/pages.html
island_backup/templates/static/island_backup.css
island_backup/templates/static/island_backup.js
island_backup-1.7.0.dist-info/DESCRIPTION.rst
island_backup-1.7.0.dist-info/METADATA
island_backup-1.7.0.dist-info/RECORD
island_backup-1.7.0.dist-info/WHEEL
island_backup-1.7.0.dist-info/entry_points.txt
island_backup-1.7.0.dist-info/metadata.json
island_backup-1.7.0.dist-info/top_level.txt
