Metadata-Version: 2.0
Name: island-backup
Version: 1.7.0
Summary: backup 4chan.org h.nimingban and kukuku.cc
Home-page: https://github.com/littlezz/island-backup
Author: littlezz
Author-email: zz.at.field@gmail.com
License: MIT
Platform: UNKNOWN
Classifier: Development Status :: 3 - Alpha
Classifier: Environment :: Web Environment
Classifier: Programming Language :: Python :: 3.5
Classifier: Programming Language :: Python :: 3 :: Only
Classifier: License :: OSI Approved :: MIT License
Requires-Dist: Jinja2
Requires-Dist: aiohttp
Requires-Dist: aiosocks
Requires-Dist: beautifulsoup4
Requires-Dist: click
Requires-Dist: docopt
Requires-Dist: tqdm
